iusql/__init__.py
iusql/clibuffer.py
iusql/clistyle.py
iusql/clitoolbar.py
iusql/compat.py
iusql/completion_refresher.py
iusql/config.py
iusql/encodingutils.py
iusql/key_bindings.py
iusql/lexer.py
iusql/main.py
iusql/sqlcompleter.py
iusql/sqlexecute.py
iusql/uptycs_restcall.py
iusql/packages/__init__.py
iusql/packages/completion_engine.py
iusql/packages/filepaths.py
iusql/packages/parseutils.py
iusql/packages/prompt_utils.py
iusql/packages/special/__init__.py
iusql/packages/special/dbcommands.py
iusql/packages/special/favoritequeries.py
iusql/packages/special/iocommands.py
iusql/packages/special/main.py
iusql/packages/special/utils.py
usql/AUTHORS
usql/__init__.py
usql/clibuffer.py
usql/clistyle.py
usql/clitoolbar.py
usql/compat.py
usql/completion_refresher.py
usql/config.py
usql/encodingutils.py
usql/key_bindings.py
usql/lexer.py
usql/main.py
usql/sqlcompleter.py
usql/sqlexecute.py
usql/uptycs_restcall.py
usql/usqlrc
usql/packages/__init__.py
usql/packages/completion_engine.py
usql/packages/filepaths.py
usql/packages/parseutils.py
usql/packages/prompt_utils.py
usql/packages/special/__init__.py
usql/packages/special/dbcommands.py
usql/packages/special/favoritequeries.py
usql/packages/special/iocommands.py
usql/packages/special/main.py
usql/packages/special/utils.py
usql-2.1.0.dist-info/LICENSE
usql-2.1.0.dist-info/METADATA
usql-2.1.0.dist-info/WHEEL
usql-2.1.0.dist-info/entry_points.txt
usql-2.1.0.dist-info/top_level.txt
usql-2.1.0.dist-info/RECORD
